LICENSE
README.md
setup.py
common/__init__.py
common/json_response.py
common/secure_util.py
common/time_util.py
ssn_common.egg-info/PKG-INFO
ssn_common.egg-info/SOURCES.txt
ssn_common.egg-info/dependency_links.txt
ssn_common.egg-info/top_level.txt