Metadata-Version: 1.1
Name: ssn-common
Version: 0.0.1
Summary: common utils
Home-page: https://github.com/chengdonglin/ssn-common
Author: chengdonglin
Author-email: chengdong2518@163.com
License: UNKNOWN
Platform: UNKNOWN
Requires: numpy
